{"main":[{"name":"3R Petroleum","area":"Petróleo e Gás - E&P","description":"3R Petroleum Oleo E Gas SA está envolvida no setor de petróleo e gás com foco no redesenvolvimento de campos de produção maduros localizados em terra. Seu objetivo é explorar, produzir e vender petróleo e seus derivados, gás natural e outros hidrocarbonetos fluidos.3R Petroleum Oleo E Gas SA está envolvida no setor de petróleo e gás com foco no redesenvolvimento de campos de produção maduros localizados em terra. Seu objetivo é explorar, produzir e vender petróleo e seus derivados, gás natural e outros hidrocarbonetos fluidos.","links":[{"title":"Website","link":"https://www.opog.com.br/"},{"title":"Site de RI","link":"http://ri.3rpetroleum.com.br/"},{"title":"Site B3","link":"https://sistemaswebb3-listados.b3.com.br/listedCompaniesPage/main/25291/RRRP/overview?language=pt-br"}]}],"info":[{"title":"Market Cap","value":"R$12.2B"},{"title":"Segmento de Listagem","value":"Novo Mercado"},{"title":"Fundação","value":"2010"},{"title":"Sede","value":"Rio de Janeiro"},{"title":"Escriturador","value":"Itaú"},{"title":"Auditoria","value":"KPMG"}],"balancesheets":[{"Ano":"12/2017","Receita Líq":"$1,345","EBITDA":"$1,345","Mrg EBITDA":"$1,345","D&A":"$1,345","EBIT":"$1,345","Res Fin":"$1,345","Impostos":"$1,345","Op Desc":"$1,345","Lucro Líq":"$1,345","Mrg Líq":"$1,345","Patrimônio":"$1,345","ROE":"$1,345","Caixa":"$1,345","Dívida":"$1,345","DL/EBITDA":"$1,345","FCO":"$1,345","Capex":"$1,345","FCF":"$1,345","FCL":"$1,345","Proventos":"$1,345","Payout":"$1,345"},{"Ano":"12/2018","Receita Líq":"$1,345","EBITDA":"$1,345","Mrg EBITDA":"$1,345","D&A":"$1,345","EBIT":"$1,345","Res Fin":"$1,345","Impostos":"$1,345","Op Desc":"$1,345","Lucro Líq":"$1,345","Mrg Líq":"$1,345","Patrimônio":"$1,345","ROE":"$1,345","Caixa":"$1,345","Dívida":"$1,345","DL/EBITDA":"$1,345","FCO":"$1,345","Capex":"$1,345","FCF":"$1,345","FCL":"$1,345","Proventos":"$1,345","Payout":"$1,345"},{"Ano":"12/2019","Receita Líq":"$1,345","EBITDA":"$1,345","Mrg EBITDA":"$1,345","D&A":"$1,345","EBIT":"$1,345","Res Fin":"$1,345","Impostos":"$1,345","Op Desc":"$1,345","Lucro Líq":"$1,345","Mrg Líq":"$1,345","Patrimônio":"$1,345","ROE":"$1,345","Caixa":"$1,345","Dívida":"$1,345","DL/EBITDA":"$1,345","FCO":"$1,345","Capex":"$1,345","FCF":"$1,345","FCL":"$1,345","Proventos":"$1,345","Payout":"$1,345"},{"Ano":"12/2020","Receita Líq":"$1,345","EBITDA":"$1,345","Mrg EBITDA":"$1,345","D&A":"$1,345","EBIT":"$1,345","Res Fin":"$1,345","Impostos":"$1,345","Op Desc":"$1,345","Lucro Líq":"$1,345","Mrg Líq":"$1,345","Patrimônio":"$1,345","ROE":"$1,345","Caixa":"$1,345","Dívida":"$1,345","DL/EBITDA":"$1,345","FCO":"$1,345","Capex":"$1,345","FCF":"$1,345","FCL":"$1,345","Proventos":"$1,345","Payout":"$1,345"},{"Ano":"12/2021","Receita Líq":"$1,345","EBITDA":"$1,345","Mrg EBITDA":"$1,345","D&A":"$1,345","EBIT":"$1,345","Res Fin":"$1,345","Impostos":"$1,345","Op Desc":"$1,345","Lucro Líq":"$1,345","Mrg Líq":"$1,345","Patrimônio":"$1,345","ROE":"$1,345","Caixa":"$1,345","Dívida":"$1,345","DL/EBITDA":"$1,345","FCO":"$1,345","Capex":"$1,345","FCF":"$1,345","FCL":"$1,345","Proventos":"$1,345","Payout":"$1,345"},{"Ano":"12/2022","Receita Líq":"$1,345","EBITDA":"$1,345","Mrg EBITDA":"$1,345","D&A":"$1,345","EBIT":"$1,345","Res Fin":"$1,345","Impostos":"$1,345","Op Desc":"$1,345","Lucro Líq":"$1,345","Mrg Líq":"$1,345","Patrimônio":"$1,345","ROE":"$1,345","Caixa":"$1,345","Dívida":"$1,345","DL/EBITDA":"$1,345","FCO":"$1,345","Capex":"$1,345","FCF":"$1,345","FCL":"$1,345","Proventos":"$1,345","Payout":"$1,345"},{"Ano":"12/2023","Receita Líq":"5,620","EBITDA":"1,886","Mrg EBITDA":"34%","D&A":"-620","EBIT":"1,266","Res Fin":"-675","Impostos":"-166","Op Desc":"0","Lucro Líq":"425","Mrg Líq":"8%","Patrimônio":"5,565","ROE":"8%","Caixa":"1,909","Dívida":"9,262","DL/EBITDA":"3.9","FCO":"1,009","Capex":"-6,147","FCF":"8,691","FCL":"-5,138","Proventos":"0","Payout":"-"},{"Ano":"06/24 TTM","Receita Líq":"$1,345","EBITDA":"$1,345","Mrg EBITDA":"$1,345","D&A":"$1,345","EBIT":"$1,345","Res Fin":"$1,345","Impostos":"$1,345","Op Desc":"$1,345","Lucro Líq":"$1,345","Mrg Líq":"$1,345","Patrimônio":"$1,345","ROE":"$1,345","Caixa":"$1,345","Dívida":"$1,345","DL/EBITDA":"$1,345","FCO":"$1,345","Capex":"$1,345","FCF":"$1,345","FCL":"$1,345","Proventos":"$1,345","Payout":"$1,345"}],"governancesheets":[{"Nome":"Total","Controlador":"-","% ON":"0%"}],"valuation":[{"title":"P/VPA","value":"2,5"},{"title":"P/R","value":"0,7"},{"title":"P/EBITDA","value":"3,8"},{"title":"P/FCO","value":"3"},{"title":"P/FCL","value":"82"},{"title":"P/L Futuro","value":"—"},{"title":"P/L","value":"—"},{"title":"VPA","value":"10,7"},{"title":"LPA","value":"—"}],"growth":[{"title":"CAGR Receita 5 anos","value":"178,3%"},{"title":"CAGR Lucro Op. 5 anos","value":"0%"},{"title":"CAGR Lucro Líq. 5 anos","value":"0%"},{"title":"CAGR LPA 5 anos","value":"0%"},{"title":"CAGR FCO 5 anos","value":"129,7%"}],"earnings":[{"title":"Dividendo por Ação","value":"0,4"},{"title":"Dividend Yield","value":"1,5%"},{"title":"Buyback Yield","value":"0%"},{"title":"Dividend Yield 5 Anos","value":"0%"},{"title":"Payout","value":"0%"},{"title":"Lucros/Prejuízos Acumulados","value":"-600,3M"}],"market_capitalization":[{"title":"Valor de Mercado","value":"12,2B"},{"title":"Valor da Firma (EV)","value":"21,8B"},{"title":"EV/Receita","value":"2,5"},{"title":"EV/EBITDA","value":"12,9"},{"title":"EV/EBITDA Ajustado","value":"10,6"},{"title":"EV/EBIT","value":"27,9"},{"title":"Δ% Total de Ações","value":"93%"}],"profitability":[{"title":"Margem Bruta","value":"30,7%"},{"title":"Margem EBITDA","value":"19,2%"},{"title":"Margem EBITDA Ajustada","value":"23,5%"},{"title":"Margem EBIT","value":"8,9%"},{"title":"Margem Líquida","value":"—"},{"title":"D&A/EBITDA","value":"53,7%"},{"title":"D&A/Normalized EBITDA","value":"43,9%"},{"title":"P&D/Receita","value":"0%"},{"title":"Capex/Receita","value":"23,4%"},{"title":"Capex/D&A","value":"3529,6%"},{"title":"Capex/FCO","value":"96,3%"},{"title":"SBC/FCO","value":"1,2%"},{"title":"-","value":"—"},{"title":"SBC/EV","value":"—"},{"title":"% Imobilizado","value":"32,6%"},{"title":"% Intangível","value":"31,2%"},{"title":"% Goodwill","value":"0%"},{"title":"ROE","value":"—"},{"title":"ROA","value":"—"},{"title":"ROIC","value":"3,2%"},{"title":"ROIC Ajustado","value":"5,5%"}],"leverage":[{"title":"Dív. Líq. com Arrendamento/EBITDA","value":"5,7"},{"title":"Dív. Líq. sem Arrendamento/EBITDA","value":"5,7"},{"title":"Dív. Líq. sem Arrendamento/OCF","value":"4,5"},{"title":"% Arrendamento","value":"0,4%"},{"title":"Dívida/Patrimônio Líq.","value":"226,5%"},{"title":"Liquidez Corrente","value":"1,4"},{"title":"Quick Ratio","value":"0,7"},{"title":"Índice de Cobertura de Juros","value":"68%"}]}