{"main":[{"name":"Tekno","area":"Siderurgia","description":"Tekno SA Industria e Comercio fabrica materiais metálicos pré-pintados utilizados para portas metálicas, painéis sanduíche, e telhados para áreas como a construção, elevadores, e câmaras frigoríficas.Tekno SA Industria e Comercio fabrica materiais metálicos pré-pintados utilizados para portas metálicas, painéis sanduíche, e telhados para áreas como a construção, elevadores, e câmaras frigoríficas.","links":[{"title":"Website","link":"https://teknokroma.com.br/"},{"title":"Site de RI","link":"https://teknokroma.com.br/relacoes-com-investidores/"},{"title":"Site B3","link":"https://sistemaswebb3-listados.b3.com.br/listedCompaniesPage/main/11231/TKNO/overview?language=pt-br"}]}],"info":[{"title":"Market Cap","value":"R$250.6M"},{"title":"Segmento de Listagem","value":"Tradicional"},{"title":"Fundação","value":"1939"},{"title":"Sede","value":"São Paulo"},{"title":"Escriturador","value":"Itaú"},{"title":"Auditoria","value":"KPMG"}],"balancesheets":[{"Ano":"12/2015","Receita Líq":"$1,345","EBITDA":"$1,345","Mrg EBITDA":"$1,345","D&A":"$1,345","EBIT":"$1,345","Res Fin":"$1,345","Impostos":"$1,345","Op Desc":"$1,345","Lucro Líq":"$1,345","Mrg Líq":"$1,345","Patrimônio":"$1,345","ROE":"$1,345","Caixa":"$1,345","Dívida":"$1,345","DL/EBITDA":"$1,345","FCO":"$1,345","Capex":"$1,345","FCF":"$1,345","FCL":"$1,345","Proventos":"$1,345","Payout":"$1,345"},{"Ano":"12/2016","Receita Líq":"$1,345","EBITDA":"$1,345","Mrg EBITDA":"$1,345","D&A":"$1,345","EBIT":"$1,345","Res Fin":"$1,345","Impostos":"$1,345","Op Desc":"$1,345","Lucro Líq":"$1,345","Mrg Líq":"$1,345","Patrimônio":"$1,345","ROE":"$1,345","Caixa":"$1,345","Dívida":"$1,345","DL/EBITDA":"$1,345","FCO":"$1,345","Capex":"$1,345","FCF":"$1,345","FCL":"$1,345","Proventos":"$1,345","Payout":"$1,345"},{"Ano":"12/2017","Receita Líq":"$1,345","EBITDA":"$1,345","Mrg EBITDA":"$1,345","D&A":"$1,345","EBIT":"$1,345","Res Fin":"$1,345","Impostos":"$1,345","Op Desc":"$1,345","Lucro Líq":"$1,345","Mrg Líq":"$1,345","Patrimônio":"$1,345","ROE":"$1,345","Caixa":"$1,345","Dívida":"$1,345","DL/EBITDA":"$1,345","FCO":"$1,345","Capex":"$1,345","FCF":"$1,345","FCL":"$1,345","Proventos":"$1,345","Payout":"$1,345"},{"Ano":"12/2018","Receita Líq":"$1,345","EBITDA":"$1,345","Mrg EBITDA":"$1,345","D&A":"$1,345","EBIT":"$1,345","Res Fin":"$1,345","Impostos":"$1,345","Op Desc":"$1,345","Lucro Líq":"$1,345","Mrg Líq":"$1,345","Patrimônio":"$1,345","ROE":"$1,345","Caixa":"$1,345","Dívida":"$1,345","DL/EBITDA":"$1,345","FCO":"$1,345","Capex":"$1,345","FCF":"$1,345","FCL":"$1,345","Proventos":"$1,345","Payout":"$1,345"},{"Ano":"12/2019","Receita Líq":"$1,345","EBITDA":"$1,345","Mrg EBITDA":"$1,345","D&A":"$1,345","EBIT":"$1,345","Res Fin":"$1,345","Impostos":"$1,345","Op Desc":"$1,345","Lucro Líq":"$1,345","Mrg Líq":"$1,345","Patrimônio":"$1,345","ROE":"$1,345","Caixa":"$1,345","Dívida":"$1,345","DL/EBITDA":"$1,345","FCO":"$1,345","Capex":"$1,345","FCF":"$1,345","FCL":"$1,345","Proventos":"$1,345","Payout":"$1,345"},{"Ano":"12/2020","Receita Líq":"$1,345","EBITDA":"$1,345","Mrg EBITDA":"$1,345","D&A":"$1,345","EBIT":"$1,345","Res Fin":"$1,345","Impostos":"$1,345","Op Desc":"$1,345","Lucro Líq":"$1,345","Mrg Líq":"$1,345","Patrimônio":"$1,345","ROE":"$1,345","Caixa":"$1,345","Dívida":"$1,345","DL/EBITDA":"$1,345","FCO":"$1,345","Capex":"$1,345","FCF":"$1,345","FCL":"$1,345","Proventos":"$1,345","Payout":"$1,345"},{"Ano":"12/2021","Receita Líq":"$1,345","EBITDA":"$1,345","Mrg EBITDA":"$1,345","D&A":"$1,345","EBIT":"$1,345","Res Fin":"$1,345","Impostos":"$1,345","Op Desc":"$1,345","Lucro Líq":"$1,345","Mrg Líq":"$1,345","Patrimônio":"$1,345","ROE":"$1,345","Caixa":"$1,345","Dívida":"$1,345","DL/EBITDA":"$1,345","FCO":"$1,345","Capex":"$1,345","FCF":"$1,345","FCL":"$1,345","Proventos":"$1,345","Payout":"$1,345"},{"Ano":"12/2022","Receita Líq":"$1,345","EBITDA":"$1,345","Mrg EBITDA":"$1,345","D&A":"$1,345","EBIT":"$1,345","Res Fin":"$1,345","Impostos":"$1,345","Op Desc":"$1,345","Lucro Líq":"$1,345","Mrg Líq":"$1,345","Patrimônio":"$1,345","ROE":"$1,345","Caixa":"$1,345","Dívida":"$1,345","DL/EBITDA":"$1,345","FCO":"$1,345","Capex":"$1,345","FCF":"$1,345","FCL":"$1,345","Proventos":"$1,345","Payout":"$1,345"},{"Ano":"12/2023","Receita Líq":"278","EBITDA":"46","Mrg EBITDA":"17%","D&A":"-6","EBIT":"40","Res Fin":"5","Impostos":"-8","Op Desc":"-1","Lucro Líq":"36","Mrg Líq":"13%","Patrimônio":"287","ROE":"13%","Caixa":"50","Dívida":"2","DL/EBITDA":"-","FCO":"40","Capex":"-16","FCF":"-12","FCL":"23","Proventos":"11","Payout":"30%"},{"Ano":"06/24 TTM","Receita Líq":"$1,345","EBITDA":"$1,345","Mrg EBITDA":"$1,345","D&A":"$1,345","EBIT":"$1,345","Res Fin":"$1,345","Impostos":"$1,345","Op Desc":"$1,345","Lucro Líq":"$1,345","Mrg Líq":"$1,345","Patrimônio":"$1,345","ROE":"$1,345","Caixa":"$1,345","Dívida":"$1,345","DL/EBITDA":"$1,345","FCO":"$1,345","Capex":"$1,345","FCF":"$1,345","FCL":"$1,345","Proventos":"$1,345","Payout":"$1,345"}],"governancesheets":[{"Nome":"ESTELA MADEIRA DO VAL","Controlador":"Sim","% ON":"26,79%","% PN":"20,55%"},{"Nome":"ELOISA MADEIRA SZANTO","Controlador":"Sim","% ON":"26,78%","% PN":"20,67%"},{"Nome":"Total","Controlador":"-","% ON":"53,57%","% PN":"41,22%"}],"valuation":[{"title":"P/VPA","value":"0,8"},{"title":"P/R","value":"0,9"},{"title":"P/EBITDA","value":"4,3"},{"title":"P/FCO","value":"5,7"},{"title":"P/FCL","value":"9"},{"title":"P/L Futuro","value":"—"},{"title":"P/L","value":"6,1"},{"title":"P/L Ajustado","value":"6,7"},{"title":"VPA","value":"100,2"},{"title":"LPA","value":"13,7"},{"title":"LPA Ajustado","value":"12,7"}],"growth":[{"title":"CAGR Receita 5 anos","value":"15,2%"},{"title":"CAGR Lucro Op. 5 anos","value":"0%"},{"title":"CAGR Lucro Líq. 5 anos","value":"118,9%"},{"title":"CAGR LPA 5 anos","value":"118,8%"},{"title":"CAGR LPA Ajustado 5 anos","value":"88,1%"},{"title":"CAGR FCO 5 anos","value":"0%"}],"earnings":[{"title":"Dividendo por Ação","value":"4,1"},{"title":"Dividend Yield","value":"4,9%"},{"title":"Buyback Yield","value":"0%"},{"title":"Dividend Yield 5 Anos","value":"0%"},{"title":"Payout","value":"29,8%"},{"title":"Lucros/Prejuízos Acumulados","value":"23,6M"}],"market_capitalization":[{"title":"Valor de Mercado","value":"250,6M"},{"title":"Valor da Firma (EV)","value":"189,9M"},{"title":"EV/Receita","value":"0,7"},{"title":"EV/EBITDA","value":"3,3"},{"title":"EV/EBITDA Ajustado","value":"3,5"},{"title":"EV/EBIT","value":"3,6"}],"profitability":[{"title":"Margem Bruta","value":"25,7%"},{"title":"Margem EBITDA","value":"20,7%"},{"title":"Margem EBITDA Ajustada","value":"19,2%"},{"title":"Margem EBIT","value":"18,5%"},{"title":"Margem Líquida","value":"14,3%"},{"title":"Margem Líquida Ajustada","value":"13,3%"},{"title":"% LL Controladores","value":"100%"},{"title":"% LL Não Controladores","value":"—"},{"title":"D&A/EBITDA","value":"10,8%"},{"title":"D&A/Normalized EBITDA","value":"11,7%"},{"title":"P&D/Receita","value":"0%"},{"title":"Capex/Receita","value":"5,7%"},{"title":"Capex/D&A","value":"1036,8%"},{"title":"Capex/FCO","value":"36,6%"},{"title":"% Imobilizado","value":"25,9%"},{"title":"% Intangível","value":"0,8%"},{"title":"% Goodwill","value":"0%"},{"title":"ROE","value":"14,3%"},{"title":"ROA","value":"10,9%"},{"title":"ROIC","value":"14,3%"},{"title":"ROIC Ajustado","value":"13,3%"}],"leverage":[{"title":"Dív. Líq. com Arrendamento/EBITDA","value":"—"},{"title":"Dív. Líq. sem Arrendamento/EBITDA","value":"—"},{"title":"Dív. Líq. sem Arrendamento/OCF","value":"—"},{"title":"% Arrendamento","value":"37,6%"},{"title":"Dívida/Patrimônio Líq.","value":"0,7%"},{"title":"Liquidez Corrente","value":"3,2"},{"title":"Quick Ratio","value":"2,1"},{"title":"Índice de Cobertura de Juros","value":"11253,3%"}]}